Metadata-Version: 2.1
Name: rechenschieber
Version: 1.0
Summary: It's a calculator
Home-page: UNKNOWN
Author: Jonas Greis
Author-email: el-toro-loco@outlook.de
License: MIT
Keywords: Taschenrechner
Platform: UNKNOWN
Classifier: Development Status :: 1 - Planning
Classifier: Intended Audience :: Developers
Classifier: Programming Language :: Python :: 3
Classifier: Operating System :: Unix
Classifier: Operating System :: MacOS :: MacOS X
Classifier: Operating System :: Microsoft :: Windows
License-File: LICENCE.txt
